pixycamev3/__init__.py
pixycamev3/pixy2.py
pixycamev3-1.0.0.dist-info/LICENSE
pixycamev3-1.0.0.dist-info/METADATA
pixycamev3-1.0.0.dist-info/WHEEL
pixycamev3-1.0.0.dist-info/top_level.txt
pixycamev3-1.0.0.dist-info/RECORD
