Metadata-Version: 2.1
Name: pixycamev3
Version: 1.0.0
Summary: Python3 API for Pixy2 on LEGO Mindstorms EV3
Home-page: https://github.com/charmedlabs/pixycamev3
Author: Kees Smit
Author-email: kwsmit@hetnet.nl
License: UNKNOWN
Project-URL: Documentation, https://docs.pixycam.com/wiki/doku.php?id=wiki:v2:python
Project-URL: Bug tracker, https://github.com/charmedlabs/pixycamev3/issues
Platform: UNKNOWN
Classifier: Programming Language :: Python :: 3
Classifier: License :: OSI Approved :: GNU General Public License v2 (GPLv2)
Classifier: Development Status :: 5 - Production/Stable
License-File: LICENSE
